aiddl_external_ros2/__init__.py
aiddl_external_ros2/util.py
aiddl_external_ros2/action/__init__.py
aiddl_external_ros2/action/nav2/__init__.py
aiddl_external_ros2/action/nav2/navigate_to_pose.py
aiddl_external_ros2/action/tutorial/__init__.py
aiddl_external_ros2/action/tutorial/fibonacci.py
aiddl_external_ros2/msg/__init__.py
aiddl_external_ros2/msg/const.py
aiddl_external_ros2/msg/builtin/__init__.py
aiddl_external_ros2/msg/builtin/const.py
aiddl_external_ros2/msg/builtin/duration.py
aiddl_external_ros2/msg/builtin/time.py
aiddl_external_ros2/msg/geometry/__init__.py
aiddl_external_ros2/msg/geometry/const.py
aiddl_external_ros2/msg/geometry/point.py
aiddl_external_ros2/msg/geometry/pose.py
aiddl_external_ros2/msg/geometry/pose_stamped.py
aiddl_external_ros2/msg/nav/__init__.py
aiddl_external_ros2/msg/nav/const.py
aiddl_external_ros2/msg/nav/map_meta_data.py
aiddl_external_ros2/msg/nav/occupancy_grid.py
aiddl_external_ros2/msg/std/__init__.py
aiddl_external_ros2/msg/std/const.py
aiddl_external_ros2/msg/std/float64.py
aiddl_external_ros2/msg/std/header.py
aiddl_external_ros2/msg/std/int64.py
aiddl_external_ros2/msg/std/string.py
aiddl_external_ros2/msg/visualization/__init__.py
aiddl_external_ros2/msg/visualization/const.py
aiddl_external_ros2/msg/visualization/marker.py
aiddl_external_ros2/service/__init__.py
aiddl_external_ros2/service/nav/__init__.py
aiddl_external_ros2/service/nav/get_map.py
aiddl_external_ros2/test/__init__.py
aiddl_external_ros2/test/test_import.py
aiddl_external_ros2-0.2.2.dist-info/LICENSE
aiddl_external_ros2-0.2.2.dist-info/METADATA
aiddl_external_ros2-0.2.2.dist-info/WHEEL
aiddl_external_ros2-0.2.2.dist-info/top_level.txt
aiddl_external_ros2-0.2.2.dist-info/RECORD
