Metadata-Version: 2.1
Name: aiddl-external-ros2
Version: 0.2.2
Summary: Library that bridges ROS2 to the AIDDL framework for integrative AI via gRPC
Home-page: http://www.aiddl.org
Author: Uwe Köckemann
Author-email: uwe.kockemann@oru.se
License: UNKNOWN
Project-URL: Bug Tracker, https://github.com/uwe-koeckemann/AIDDL/issues
Platform: UNKNOWN
Classifier: Programming Language :: Python :: 3
Classifier: License :: OSI Approved :: MIT License
Classifier: Operating System :: OS Independent
Requires-Python: >=3.7
License-File: LICENSE
Requires-Dist: aiddl-core (>=0.3.0)
Requires-Dist: aiddl-external-grpc (>=0.2.2)
